quotientai/__init__.py
quotientai/_constants.py
quotientai/async_client.py
quotientai/cli/__init__.py
quotientai/cli/entrypoint.py
quotientai/client.py
quotientai/exceptions.py
quotientai/resources/__init__.py
quotientai/resources/auth.py
quotientai/resources/logs.py
quotientai/resources/tracing.py
quotientai/tracing/__init__.py
quotientai/tracing/core.py
quotientai/tracing/instrumentation/README.md
quotientai/tracing/instrumentation/__init__.py
quotientai/tracing/instrumentation/base.py
quotientai/tracing/instrumentation/chroma.py
quotientai/tracing/instrumentation/pinecone.py
quotientai/tracing/instrumentation/qdrant.py
quotientai/types.py
quotientai-0.4.17.dist-info/METADATA
quotientai-0.4.17.dist-info/WHEEL
quotientai-0.4.17.dist-info/entry_points.txt
quotientai-0.4.17.dist-info/licenses/LICENSE
quotientai-0.4.17.dist-info/RECORD
