Metadata-Version: 2.4
Name: quotientai
Version: 0.4.17
Summary: Python library for tracing, logging, and detecting problems with AI Agents
License: Apache-2.0
License-File: LICENSE
Keywords: quotient,evaluation,llms,machine learning,ai,logging,tracing,hallucinations
Author: Freddie Vargus
Author-email: freddie@quotientai.co
Requires-Python: >=3.9,<4.0
Classifier: License :: OSI Approved :: Apache Software License
Classifier: Programming Language :: Python :: 3
Classifier: Programming Language :: Python :: 3.9
Classifier: Programming Language :: Python :: 3.10
Classifier: Programming Language :: Python :: 3.11
Classifier: Programming Language :: Python :: 3.12
Classifier: Programming Language :: Python :: 3.13
Classifier: Programming Language :: Python :: 3.14
Requires-Dist: click (>=8.1.7,<9.0.0)
Requires-Dist: httpx (>=0.27.0)
Requires-Dist: opentelemetry-exporter-otlp (>=1.34.0,<2.0.0)
Requires-Dist: opentelemetry-sdk (>=1.34.0,<2.0.0)
Requires-Dist: pydantic (>=2.10.6)
Requires-Dist: pyjwt (>=2.10.1,<3.0.0)
Requires-Dist: rich (>=13.7.0,<14.0.0)
Requires-Dist: tenacity (>=9.0.0)
Requires-Dist: typer (>=0.16.0)
